tibber/__init__.py
tibber/account.py
tibber/exceptions/__init__.py
tibber/exceptions/api.py
tibber/networking/__init__.py
tibber/networking/query_builder.py
tibber/networking/query_executor.py
tibber/types/__init__.py
tibber/types/address.py
tibber/types/consumption.py
tibber/types/contact_info.py
tibber/types/home.py
tibber/types/home_consumption_connection.py
tibber/types/home_consumption_edge.py
tibber/types/home_consumption_page_info.py
tibber/types/home_features.py
tibber/types/home_production_connection.py
tibber/types/home_production_edge.py
tibber/types/home_production_page_info.py
tibber/types/legal_entity.py
tibber/types/live_measurement.py
tibber/types/metering_point_data.py
tibber/types/price.py
tibber/types/price_info.py
tibber/types/price_rating.py
tibber/types/price_rating_entry.py
tibber/types/price_rating_threshold_percentages.py
tibber/types/price_rating_type.py
tibber/types/production.py
tibber/types/push_notification_response.py
tibber/types/subscription.py
tibber/types/subscription_price_connection.py
tibber/types/subscription_price_connection_page_info.py
tibber/types/subscription_price_edge.py
tibber/types/viewer.py
tibber_py-0.7.1.dist-info/licenses/LICENSE
tibber_py-0.7.1.dist-info/METADATA
tibber_py-0.7.1.dist-info/WHEEL
tibber_py-0.7.1.dist-info/top_level.txt
tibber_py-0.7.1.dist-info/RECORD
