Metadata-Version: 2.4
Name: tibber.py
Version: 0.7.1
Summary: A python wrapper for the Tibber API.
Home-page: https://tibberpy.readthedocs.io/en/latest/
Author: BeatsuDev
Author-email: 
License: MIT
Classifier: Development Status :: 1 - Planning
Classifier: Intended Audience :: Developers
Classifier: License :: OSI Approved :: MIT License
Classifier: Natural Language :: English
Classifier: Operating System :: OS Independent
Classifier: Programming Language :: Python :: 3
Classifier: Topic :: Documentation :: Sphinx
Classifier: Topic :: Home Automation
Classifier: Topic :: Software Development :: Libraries :: Python Modules
Requires-Python: >=3.9.0
License-File: LICENSE
Requires-Dist: gql==3.5.3
Requires-Dist: gql[aiohttp]>=3.4.0
Requires-Dist: gql[websockets]>=3.4.0
Requires-Dist: graphql-core>=3.2.3
Requires-Dist: backoff>=2.2.1
Requires-Dist: asyncio-atexit>=1.0.1
Dynamic: author
Dynamic: classifier
Dynamic: description
Dynamic: description-content-type
Dynamic: home-page
Dynamic: license
Dynamic: license-file
Dynamic: requires-dist
Dynamic: requires-python
Dynamic: summary
